slotscheck/__init__.py
slotscheck/__main__.py
slotscheck/checks.py
slotscheck/cli.py
slotscheck/common.py
slotscheck/config.py
slotscheck/discovery.py
slotscheck/py.typed
slotscheck-0.19.0.dist-info/LICENSE
slotscheck-0.19.0.dist-info/METADATA
slotscheck-0.19.0.dist-info/WHEEL
slotscheck-0.19.0.dist-info/entry_points.txt
slotscheck-0.19.0.dist-info/RECORD
