Metadata-Version: 2.1
Name: slotscheck
Version: 0.19.0
Summary: Ensure your __slots__ are working properly.
Home-page: https://github.com/ariebovenberg/slotscheck
License: MIT
Author: Arie Bovenberg
Author-email: a.c.bovenberg@gmail.com
Requires-Python: >=3.8.1
Classifier: License :: OSI Approved :: MIT License
Classifier: Programming Language :: Python :: 3
Classifier: Programming Language :: Python :: 3.9
Classifier: Programming Language :: Python :: 3.10
Classifier: Programming Language :: Python :: 3.11
Classifier: Programming Language :: Python :: 3.12
Classifier: Programming Language :: Python :: 3.8
Classifier: Programming Language :: Python :: Implementation :: CPython
Classifier: Topic :: Software Development :: Quality Assurance
Classifier: Typing :: Typed
Requires-Dist: click (>=8.0,<9.0)
Requires-Dist: tomli (>=0.2.6,<3.0.0) ; python_version < "3.11"
Project-URL: Repository, https://github.com/ariebovenberg/slotscheck
